jupysub/__init__.py
jupysub/_version.py
jupysub/jupysub.py
jupysub/utils/NotebookManipulator.py
jupysub/utils/__init__.py
jupysub/utils/add_expected_outputs.py
jupysub/utils/difficulty_bar.py
jupysub/utils/documentation_replacer.py
jupysub/utils/tags.py
jupysub/utils/json/_abbreviations.json
jupysub/utils/json/_info.json
jupysub/utils/json/_links.json
jupysub/utils/json/abc.json
jupysub/utils/json/aifc.json
jupysub/utils/json/argparse.json
jupysub/utils/json/array.json
jupysub/utils/json/ast.json
jupysub/utils/json/asynchat.json
jupysub/utils/json/asyncio.json
jupysub/utils/json/asyncore.json
jupysub/utils/json/atexit.json
jupysub/utils/json/audioop.json
jupysub/utils/json/base64.json
jupysub/utils/json/bdb.json
jupysub/utils/json/binascii.json
jupysub/utils/json/bisect.json
jupysub/utils/json/bz2.json
jupysub/utils/json/calendar.json
jupysub/utils/json/cgi.json
jupysub/utils/json/cgitb.json
jupysub/utils/json/chunk.json
jupysub/utils/json/cmath.json
jupysub/utils/json/cmd.json
jupysub/utils/json/code.json
jupysub/utils/json/codecs.json
jupysub/utils/json/codeop.json
jupysub/utils/json/collections.json
jupysub/utils/json/colorsys.json
jupysub/utils/json/compileall.json
jupysub/utils/json/concurrent.json
jupysub/utils/json/configparser.json
jupysub/utils/json/contextlib.json
jupysub/utils/json/contextvars.json
jupysub/utils/json/copy.json
jupysub/utils/json/copyreg.json
jupysub/utils/json/crypt.json
jupysub/utils/json/csv.json
jupysub/utils/json/ctypes.json
jupysub/utils/json/curses.json
jupysub/utils/json/dataclasses.json
jupysub/utils/json/datetime.json
jupysub/utils/json/dbm.json
jupysub/utils/json/decimal.json
jupysub/utils/json/difflib.json
jupysub/utils/json/dis.json
jupysub/utils/json/doctest.json
jupysub/utils/json/email.json
jupysub/utils/json/encodings.json
jupysub/utils/json/ensurepip.json
jupysub/utils/json/enum.json
jupysub/utils/json/faulthandler.json
jupysub/utils/json/filecmp.json
jupysub/utils/json/fileinput.json
jupysub/utils/json/fnmatch.json
jupysub-0.3.0.dist-info/METADATA
jupysub-0.3.0.dist-info/WHEEL
jupysub-0.3.0.dist-info/entry_points.txt
jupysub-0.3.0.dist-info/top_level.txt
jupysub-0.3.0.dist-info/RECORD
