Metadata-Version: 2.1
Name: jupysub
Version: 0.3.0
Summary: JuPySub
Author-email: Pedro de Carvalho Ferreira <p.h.d.carvalho.ferreira@student.tue.nl>, Ivo Filot <i.a.w.filot@tue.nl>, Ivo Roghair <i.roghair@tue.nl>
Maintainer-email: Ivo Filot <i.a.w.filot@tue.nl>
License: GPL-3.0-or-later
Project-URL: Homepage, https://gitlab.tue.nl/cec-cbl-programming/jupysub
Project-URL: Bug Tracker, https://gitlab.tue.nl/cec-cbl-programming/jupysub/-/issues
Classifier: Programming Language :: Python :: 3
Classifier: Operating System :: OS Independent
Requires-Python: >=3.7
Requires-Dist: nbconvert
Requires-Dist: nbformat
Requires-Dist: ipython
Requires-Dist: ipykernel
